<?xml version="1.0" encoding="utf-8" ?>
<dwsync>
<file name="cover.jpg" server="us104.siteground.us" local="131575775133079545" remote="131576689800000000" Dst="1" />
<file name="cover2.jpg" server="us104.siteground.us" local="131542930742144769" remote="131576689800000000" Dst="1" />
<file name="in-progress.png" server="us104.siteground.us" local="131542908384637103" remote="131576689800000000" Dst="1" />
<file name="production.jpg" server="us104.siteground.us" local="131542915381043272" remote="131576689800000000" Dst="1" />
<file name="sketches.jpg" server="us104.siteground.us" local="131529183256402627" remote="131576689800000000" Dst="1" />
<file name="spread2_mission.jpg" server="us104.siteground.us" local="131534379618654944" remote="131576689800000000" Dst="1" />
<file name="spread_colors.jpg" server="us104.siteground.us" local="131529184936024921" remote="131576689800000000" Dst="1" />
<file name="spread_logo-slant.jpg" server="us104.siteground.us" local="131529184060981024" remote="131576689800000000" Dst="1" />
<file name="use-sq.jpg" server="us104.siteground.us" local="131575159763525820" remote="131576689800000000" Dst="1" />
<file name="use.jpg" server="us104.siteground.us" local="131530752544411494" remote="131576689800000000" Dst="1" />
</dwsync>